src/__init__.py
src/main.py
mosmetro_test_package2-0.1.0.dist-info/METADATA
mosmetro_test_package2-0.1.0.dist-info/WHEEL
mosmetro_test_package2-0.1.0.dist-info/RECORD
