Metadata-Version: 2.3
Name: mosmetro_test_package2
Version: 0.1.0
Summary: Тестовый пакет-зависимость
License: MIT
Author: Large Pemp
Author-email: qwe@qwe.qwe
Requires-Python: >=3.10,<4.0
Classifier: Development Status :: 4 - Beta
Classifier: License :: OSI Approved :: MIT License
Classifier: Programming Language :: Python :: 3
Classifier: Programming Language :: Python :: 3.10
Classifier: Programming Language :: Python :: 3.11
Classifier: Programming Language :: Python :: 3.12
Classifier: Programming Language :: Python :: 3.13
